ytdoc/__init__.py
ytdoc/main.py
youtube_doc-0.1.0.dist-info/METADATA
youtube_doc-0.1.0.dist-info/WHEEL
youtube_doc-0.1.0.dist-info/entry_points.txt
youtube_doc-0.1.0.dist-info/top_level.txt
youtube_doc-0.1.0.dist-info/RECORD
