Metadata-Version: 2.1
Name: youtube-doc
Version: 0.1.0
Summary: A helper package for creating title and description for your YouTube videos based on transcription.
Home-page: https://github.com/gomleksiz/youtube-doc
Author: Huseyin Gomleksizoglu
Author-email: huseyim@gmail.com
License: MIT
Keywords: youtube video helper library
Classifier: Development Status :: 3 - Alpha
Classifier: Intended Audience :: Developers
Classifier: Topic :: Software Development :: Libraries
Classifier: License :: OSI Approved :: MIT License
Classifier: Programming Language :: Python :: 3
Classifier: Programming Language :: Python :: 3.7
Classifier: Programming Language :: Python :: 3.8
Classifier: Programming Language :: Python :: 3.9
Classifier: Programming Language :: Python :: 3.10
